{
    "activation": {
        "Thanks": "{{1}} मध्ये आपले स्वागत आहे",
        "ReallyYourEmail": "हा खरोखर तुमचा ईमेल पत्ता आहे का, {{1}}? तसे असल्यास, तुमचा सांकेतिक वाक्यांश सेट करण्यासाठी आणि तुमचे खाते सक्रिय करण्यासाठी येथे क्लिक <a href='{{2}}'>करा<\/a> .",
        "SeeYou": "<a href='{{1}}'>{{2}}<\/a> वर भेटू!"
    },
    "LinkToUnsubscribe": "तुम्हाला आणखी ईमेल मिळवायचे नसल्यास <a href='{{1}}'>सदस्यत्व रद्द<\/a> करण्यासाठी येथे एक लिंक आहे.",
    "Greetings": "{{1}} कडून शुभेच्छा.",
    "SeeHistory": "{{1}} साठी पेमेंट इतिहास पहा",
    "charge": {
        "HasBeenCharged": "अहो, हे तुम्हाला कळवण्यासाठी आहे की {{1}} कडून {{3}} साठी {{2}} शुल्क आकारले गेले आहे {{4}}"
    },
    "charged": {
        "HavePaid": "अहो {{1}}, हे फक्त एक द्रुत पुष्टीकरण आहे की तुम्ही {{4}} साठी {{3}} ला यशस्वीरित्या {{2}} पैसे दिले आहेत."
    },
    "resend": {
        "Thanks": "{{1}} ला भेट दिल्याबद्दल धन्यवाद",
        "YouAreReceiving": "तुम्ही हा ईमेल प्राप्त करत आहात कारण कोणीतरी तुमचा ईमेल पत्ता प्रविष्ट केला आणि &quot;पासफ्रेज विसरला&quot; वर क्लिक केले. ते तुम्ही नसल्यास, फक्त या संदेशाकडे दुर्लक्ष करा.",
        "Reset": "तुमचा सांकेतिक वाक्यांश रीसेट करण्यासाठी, {{1}} वर क्लिक करा",
        "SetUpPassphrase": "सांकेतिक वाक्यांश सेट करा"
    },
    "subscription": {
        "YouHaveStarted": "अहो {{1}}, तुम्ही तुमचे {{2}} सदस्यत्व {{3}} सह {{4}} वाजता {{5}} महिन्यांसाठी सुरू केले आहे.",
        "HasStarted": "हे फक्त तुम्हाला कळवण्यासाठी आहे {{1}} ने {{3}} ची {{3}} {{5}} महिन्यांसाठी {{4}} सदस्यता सुरू केली आहे."
    },
    "SeeYou": "{{1}} वर भेटू!"
}